{
    "chances": {
        "equipment": {
            "FirstPrimaryWeapon": 100
        },
        "weaponMods": {
            "mod_barrel": 100,
            "mod_handguard": 100,
            "mod_stock": 100
        }
    },
    "inventory": {
        "equipment": {
            "FirstPrimaryWeapon": {
                "691098356f593043295f6ddc": 1,
                "6910e86bbcb9218635891ae2": 1
            }
        },
        "mods": {
            "691098356f593043295f6ddc": {
                "mod_barrel": [
                    "6910d6c97e9a164e15f94d48"
                ],
                "mod_stock": [
                    "61f803b8ced75b2e852e35f8",
                    "61f7b234ea4ab34f2f59c3ec"
                ]
            },
            "6910d6c97e9a164e15f94d48": {
                "mod_handguard": [
                    "61f8024263dc1250e26eb029",
                    "61f7b85367ddd414173fdb36"
                ]
            },
            "6910e86bbcb9218635891ae2": {
                "mod_barrel": [
                    "6910e8d90b57259e9dd34f78"
                ],
                "mod_stock": [
                    "611a31ce5b7ffe001b4649d1"
                ]
            }
        },
        "Ammo": {
            "Caliber12g": {
                "5c0d591486f7744c505b416f": 5,
                "698924bf6dcd41ac313f5921": 10,
                "699358094978fa2d65f4dcf3": 1
            },
            "Caliber17.8×89": {
                "6910e1cbbd20f63a9791742e": 1
            }
        }
    }
}